hardware/memory/program_counter.v
// 16 bit program counter
module PROGRAM_COUNTER_16 (
    input clk, 
    input reset_n, 
    input load, 
    input inc, 
    input [15:0] data_in, 
    output [15:0] data_out
);
    reg [15:0] pc_value = 0;

    always @(posedge clk) begin
        if (!reset_n) begin
            pc_value <= {16{1'b0}}; 
        end else if (inc) begin
            pc_value <= pc_value + 1; 
        end else if(load) begin
            pc_value <= data_in; 
        end
    end
    assign data_out = pc_value; 
endmodule

hardware/memory/program_counter_tb.v
`timescale 1ns/100ps // define the minimum time unit used by the simulation

module program_counter_tb; 
    reg _clk=0; 
    wire clk; 

    reg reset_n = 1; // set value to 0 to reset(pull down like in real hardware)
    reg inc = 1; 
    reg load = 0; 

    realtime capture = 0.0;

    always #5 _clk=~_clk; // invert clock every 5 ns
    assign clk = _clk; 

    reg [15:0] data_in16 = {16{1'b0}}; 
    wire [15:0] data_out16; 

    PROGRAM_COUNTER_16 pc_16(clk, reset_n, load, inc, data_in16, data_out16); 

    initial begin
        forever begin
            #2; 
            data_in16 = ~data_in16; 
            // capture = $realtime;
            // $display("%t", capture); // uncomment to print the cycle count of the simulation in realtime.
        end
    end

    initial begin
        $display("PROGRAM COUNTER TESTBENCH"); 
        $dumpfile("program_counter-dump.vcd");
        $dumpvars(3);
        #100000 // run simulation for 100000 timeunits (in this case 100000 ns as defined on top)
        $display("VISUALISE THE SIMULATION ON GTKWAVE USING THE .vcd OUTPUT"); 
        $finish;
    end 
endmodule

hardware/memory/program_counter-dump.vcd
$date
	Thu May  2 15:35:51 2024
$end
$version
	Icarus Verilog
$end
$timescale
	100ps
$end
$scope module program_counter_tb $end
$var wire 1 ! clk $end
$var wire 16 " data_out16 [15:0] $end
$var reg 1 # _clk $end
$var reg 16 $ data_in16 [15:0] $end
$var reg 1 % inc $end
$var reg 1 & load $end
$var reg 1 ' reset_n $end
$var real 1 ( capture $end
$scope module pc_16 $end
$var wire 1 ! clk $end
$var wire 16 ) data_in [15:0] $end
$var wire 16 * data_out [15:0] $end
$var wire 1 % inc $end
$var wire 1 & load $end
$var wire 1 ' reset_n $end
$var reg 16 + pc_value [15:0] $end
$upscope $end
$upscope $end
$enddefinitions $end
$comment Show the parameter values. $end
$dumpall
$end
#0
$dumpvars
b0 +
b0 *
b0 )
r0 (
1'
0&
1%
b0 $
0#
b0 "
0!
$end
#20
b1111111111111111 $
b1111111111111111 )
#40
b0 $
b0 )
#50
b1 "
b1 *
b1 +
1!
1#
#60
b1111111111111111 $
b1111111111111111 )
#80
b0 $
b0 )
#100
b1111111111111111 $
b1111111111111111 )
0!
0#
#120
b0 $
b0 )
#140
b1111111111111111 $
b1111111111111111 )
#150
b10 "
b10 *
b10 +
1!
1#
#160
b0 $
b0 )
#180
b1111111111111111 $
b1111111111111111 )
#200
b0 $
b0 )
0!
0#
#220
b1111111111111111 $
b1111111111111111 )
#240
b0 $
b0 )
#250
b11 "
b11 *
b11 +
1!
1#
#260
b1111111111111111 $
b1111111111111111 )
#280
b0 $
b0 )
#300
b1111111111111111 $
b1111111111111111 )
0!
0#
#320
b0 $
b0 )
#340
b1111111111111111 $
b1111111111111111 )
#350
b100 "
b100 *
b100 +
1!
1#
#360
b0 $
b0 )
#380
b1111111111111111 $
b1111111111111111 )
#400
b0 $
b0 )
0!
0#
#420
b1111111111111111 $
b1111111111111111 )
#440
b0 $
b0 )
#450
b101 "
b101 *
b101 +
1!
1#
#460
b1111111111111111 $
b1111111111111111 )
#480
b0 $
b0 )
#500
b1111111111111111 $
b1111111111111111 )
0!
0#
#520
b0 $
b0 )
#540
b1111111111111111 $
b1111111111111111 )
#550
b110 "
b110 *
b110 +
1!
1#
#560
b0 $
b0 )
#580
b1111111111111111 $
b1111111111111111 )
#600
b0 $
b0 )
0!
0#
#620
b1111111111111111 $
b1111111111111111 )
#640
b0 $
b0 )
#650
b111 "
b111 *
b111 +
1!
1#
#660
b1111111111111111 $
b1111111111111111 )
#680
b0 $
b0 )
#700
b1111111111111111 $
b1111111111111111 )
0!
0#
#720
b0 $
b0 )
#740
b1111111111111111 $
b1111111111111111 )
#750
b1000 "
b1000 *
b1000 +
1!
1#
#760
b0 $
b0 )
#780
b1111111111111111 $
b1111111111111111 )
#800
b0 $
b0 )
0!
0#
#820
b1111111111111111 $
b1111111111111111 )
#840
b0 $
b0 )
#850
b1001 "
b1001 *
b1001 +
1!
1#
#860
b1111111111111111 $
b1111111111111111 )
#880
b0 $
b0 )
#900
b1111111111111111 $
b1111111111111111 )
0!
0#
#920
b0 $
b0 )
#940
b1111111111111111 $
b1111111111111111 )
#950
b1010 "
b1010 *
b1010 +
1!
1#
#960
b0 $
b0 )
#980
b1111111111111111 $
b1111111111111111 )
#1000
b0 $
b0 )
0!
0#
#1020
b1111111111111111 $
b1111111111111111 )
#1040
b0 $
b0 )
#1050
b1011 "
b1011 *
b1011 +
1!
1#
#1060
b1111111111111111 $
b1111111111111111 )
#1080
b0 $
b0 )
#1100
b1111111111111111 $
b1111111111111111 )
0!
0#
#1120
b0 $
b0 )
#1140
b1111111111111111 $
b1111111111111111 )
#1150
b1100 "
b1100 *
b1100 +
1!
1#
#1160
b0 $
b0 )
#1180
b1111111111111111 $
b1111111111111111 )
#1200
b0 $
b0 )
0!
0#
#1220
b1111111111111111 $
b1111111111111111 )
#1240
b0 $
b0 )
#1250
b1101 "
b1101 *
b1101 +
1!
1#
#1260
b1111111111111111 $
b1111111111111111 )
#1280
b0 $
b0 )
#1300
b1111111111111111 $
b1111111111111111 )
0!
0#
#1320
b0 $
b0 )
#1340
b1111111111111111 $
b1111111111111111 )
#1350
b1110 "
b1110 *
b1110 +
1!
1#
#1360
b0 $
b0 )
#1380
b1111111111111111 $
b1111111111111111 )
#1400
b0 $
b0 )
0!
0#
#1420
b1111111111111111 $
b1111111111111111 )
#1440
b0 $
b0 )
#1450
b1111 "
b1111 *
b1111 +
1!
1#
#1460
b1111111111111111 $
b1111111111111111 )
#1480
b0 $
b0 )
#1500
b1111111111111111 $
b1111111111111111 )
0!
0#
#1520
b0 $
b0 )
#1540
b1111111111111111 $
b1111111111111111 )
#1550
b10000 "
b10000 *
b10000 +
1!
1#
#1560
b0 $
b0 )
#1580
b1111111111111111 $
b1111111111111111 )
#1600
b0 $
b0 )
0!
0#
#1620
b1111111111111111 $
b1111111111111111 )
#1640
b0 $
b0 )
#1650
b10001 "
b10001 *
b10001 +
1!
1#
#1660
b1111111111111111 $
b1111111111111111 )
#1680
b0 $
b0 )
#1700
b1111111111111111 $
b1111111111111111 )
0!
0#
#1720
b0 $
b0 )
#1740
b1111111111111111 $
b1111111111111111 )
#1750
b10010 "
b10010 *
b10010 +
1!
1#
#1760
b0 $
b0 )
#1780
b1111111111111111 $
b1111111111111111 )
#1800
b0 $
b0 )
0!
0#
#1820
b1111111111111111 $
b1111111111111111 )
#1840
b0 $
b0 )
#1850
b10011 "
b10011 *
b10011 +
1!
1#
#1860
b1111111111111111 $
b1111111111111111 )
#1880
b0 $
b0 )
#1900
b1111111111111111 $
b1111111111111111 )
0!
0#
#1920
b0 $
b0 )
#1940
b1111111111111111 $
b1111111111111111 )
#1950
b10100 "
b10100 *
b10100 +
1!
1#
#1960
b0 $
b0 )
#1980
b1111111111111111 $
b1111111111111111 )
#2000
b0 $
b0 )
0!
0#
#2020
b1111111111111111 $
b1111111111111111 )
#2040
b0 $
b0 )
#2050
b10101 "
b10101 *
b10101 +
1!
1#
#2060
b1111111111111111 $
b1111111111111111 )
#2080
b0 $
b0 )
#2100
b1111111111111111 $
b1111111111111111 )
0!
0#
#2120
b0 $
b0 )
#2140
b1111111111111111 $
b1111111111111111 )
#2150
b10110 "
b10110 *
b10110 +
1!
1#
#2160
b0 $
b0 )
#2180
b1111111111111111 $
b1111111111111111 )
#2200
b0 $
b0 )
0!
0#
#2220
b1111111111111111 $
b1111111111111111 )
#2240
b0 $
b0 )
#2250
b10111 "
b10111 *
b10111 +
1!
1#
#2260
b1111111111111111 $
b1111111111111111 )
#2280
b0 $
b0 )
#2300
b1111111111111111 $
b1111111111111111 )
0!
0#
#2320
b0 $
b0 )
#2340
b1111111111111111 $
b1111111111111111 )
#2350
b11000 "
b11000 *
b11000 +
1!
1#
#2360
b0 $
b0 )
#2380
b1111111111111111 $
b1111111111111111 )
#2400
b0 $
b0 )
0!
0#
#2420
b1111111111111111 $
b1111111111111111 )
#2440
b0 $
b0 )
#2450
b11001 "
b11001 *
b11001 +
1!
1#
#2460
b1111111111111111 $
b1111111111111111 )
#2480
b0 $
b0 )
#2500
b1111111111111111 $
b1111111111111111 )
0!
0#
#2520
b0 $
b0 )
#2540
b1111111111111111 $
b1111111111111111 )
#2550
b11010 "
b11010 *
b11010 +
1!
1#
#2560
b0 $
b0 )
#2580
b1111111111111111 $
b1111111111111111 )
#2600
b0 $
b0 )
0!
0#
#2620
b1111111111111111 $
b1111111111111111 )
#2640
b0 $
b0 )
#2650
b11011 "
b11011 *
b11011 +
1!
1#
#2660
b1111111111111111 $
b1111111111111111 )
#2680
b0 $
b0 )
#2700
b1111111111111111 $
b1111111111111111 )
0!
0#
#2720
b0 $
b0 )
#2740
b1111111111111111 $
b1111111111111111 )
#2750
b11100 "
b11100 *
b11100 +
1!
1#
#2760
b0 $
b0 )
#2780
b1111111111111111 $
b1111111111111111 )
#2800
b0 $
b0 )
0!
0#
#2820
b1111111111111111 $
b1111111111111111 )
#2840
b0 $
b0 )
#2850
b11101 "
b11101 *
b11101 +
1!
1#
#2860
b1111111111111111 $
b1111111111111111 )
#2880
b0 $
b0 )
#2900
b1111111111111111 $
b1111111111111111 )
0!
0#
#2920
b0 $
b0 )
#2940
b1111111111111111 $
b1111111111111111 )
#2950
b11110 "
b11110 *
b11110 +
1!
1#
#2960
b0 $
b0 )
#2980
b1111111111111111 $
b1111111111111111 )
#3000
b0 $
b0 )
0!
0#
#3020
b1111111111111111 $
b1111111111111111 )
#3040
b0 $
b0 )
#3050
b11111 "
b11111 *
b11111 +
1!
1#
#3060
b1111111111111111 $
b1111111111111111 )
#3080
b0 $
b0 )
#3100
b1111111111111111 $
b1111111111111111 )
0!
0#
#3120
b0 $
b0 )
#3140
b1111111111111111 $
b1111111111111111 )
#3150
b100000 "
b100000 *
b100000 +
1!
1#
#3160
b0 $
b0 )
#3180
b1111111111111111 $
b1111111111111111 )
#3200
b0 $
b0 )
0!
0#
#3220
b1111111111111111 $
b1111111111111111 )
#3240
b0 $
b0 )
#3250
b100001 "
b100001 *
b100001 +
1!
1#
#3260
b1111111111111111 $
b1111111111111111 )
#3280
b0 $
b0 )
#3300
b1111111111111111 $
b1111111111111111 )
0!
0#
#3320
b0 $
b0 )
#3340
b1111111111111111 $
b1111111111111111 )
#3350
b100010 "
b100010 *
b100010 +
1!
1#
#3360
b0 $
b0 )
#3380
b1111111111111111 $
b1111111111111111 )
#3400
b0 $
b0 )
0!
0#
#3420
b1111111111111111 $
b1111111111111111 )
#3440
b0 $
b0 )
#3450
b100011 "
b100011 *
b100011 +
1!
1#
#3460
b1111111111111111 $
b1111111111111111 )
#3480
b0 $
b0 )
#3500
b1111111111111111 $
b1111111111111111 )
0!
0#
#3520
b0 $
b0 )
#3540
b1111111111111111 $
b1111111111111111 )
#3550
b100100 "
b100100 *
b100100 +
1!
1#
#3560
b0 $
b0 )
#3580
b1111111111111111 $
b1111111111111111 )
#3600
b0 $
b0 )
0!
0#
#3620
b1111111111111111 $
b1111111111111111 )
#3640
b0 $
b0 )
#3650
b100101 "
b100101 *
b100101 +
1!
1#
#3660
b1111111111111111 $
b1111111111111111 )
#3680
b0 $
b0 )
#3700
b1111111111111111 $
b1111111111111111 )
0!
0#
#3720
b0 $
b0 )
#3740
b1111111111111111 $
b1111111111111111 )
#3750
b100110 "
b100110 *
b100110 +
1!
1#
#3760
b0 $
b0 )
#3780
b1111111111111111 $
b1111111111111111 )
#3800
b0 $
b0 )
0!
0#
#3820
b1111111111111111 $
b1111111111111111 )
#3840
b0 $
b0 )
#3850
b100111 "
b100111 *
b100111 +
1!
1#
#3860
b1111111111111111 $
b1111111111111111 )
#3880
b0 $
b0 )
#3900
b1111111111111111 $
b1111111111111111 )
0!
0#
#3920
b0 $
b0 )
#3940
b1111111111111111 $
b1111111111111111 )
#3950
b101000 "
b101000 *
b101000 +
1!
1#
#3960
b0 $
b0 )
#3980
b1111111111111111 $
b1111111111111111 )
#4000
b0 $
b0 )
0!
0#
#4020
b1111111111111111 $
b1111111111111111 )
#4040
b0 $
b0 )
#4050
b101001 "
b101001 *
b101001 +
1!
1#
#4060
b1111111111111111 $
b1111111111111111 )
#4080
b0 $
b0 )
#4100
b1111111111111111 $
b1111111111111111 )
0!
0#
#4120
b0 $
b0 )
#4140
b1111111111111111 $
b1111111111111111 )
#4150
b101010 "
b101010 *
b101010 +
1!
1#
#4160
b0 $
b0 )
#4180
b1111111111111111 $
b1111111111111111 )
#4200
b0 $
b0 )
0!
0#
#4220
b1111111111111111 $
b1111111111111111 )
#4240
b0 $
b0 )
#4250
b101011 "
b101011 *
b101011 +
1!
1#
#4260
b1111111111111111 $
b1111111111111111 )
#4280
b0 $
b0 )
#4300
b1111111111111111 $
b1111111111111111 )
0!
0#
#4320
b0 $
b0 )
#4340
b1111111111111111 $
b1111111111111111 )
#4350
b101100 "
b101100 *
b101100 +
1!
1#
#4360
b0 $
b0 )
#4380
b1111111111111111 $
b1111111111111111 )
#4400
b0 $
b0 )
0!
0#
#4420
b1111111111111111 $
b1111111111111111 )
#4440
b0 $
b0 )
#4450
b101101 "
b101101 *
b101101 +
1!
1#
#4460
b1111111111111111 $
b1111111111111111 )
#4480
b0 $
b0 )
#4500
b1111111111111111 $
b1111111111111111 )
0!
0#
#4520
b0 $
b0 )
#4540
b1111111111111111 $
b1111111111111111 )
#4550
b101110 "
b101110 *
b101110 +
1!
1#
#4560
b0 $
b0 )
#4580
b1111111111111111 $
b1111111111111111 )
#4600
b0 $
b0 )
0!
0#
#4620
b1111111111111111 $
b1111111111111111 )
#4640
b0 $
b0 )
#4650
b101111 "
b101111 *
b101111 +
1!
1#
#4660
b1111111111111111 $
b1111111111111111 )
#4680
b0 $
b0 )
#4700
b1111111111111111 $
b1111111111111111 )
0!
0#
#4720
b0 $
b0 )
#4740
b1111111111111111 $
b1111111111111111 )
#4750
b110000 "
b110000 *
b110000 +
1!
1#
#4760
b0 $
b0 )
#4780
b1111111111111111 $
b1111111111111111 )
#4800
b0 $
b0 )
0!
0#
#4820
b1111111111111111 $
b1111111111111111 )
#4840
b0 $
b0 )
#4850
b110001 "
b110001 *
b110001 +
1!
1#
#4860
b1111111111111111 $
b1111111111111111 )
#4880
b0 $
b0 )
#4900
b1111111111111111 $
b1111111111111111 )
0!
0#
#4920
b0 $
b0 )
#4940
b1111111111111111 $
b1111111111111111 )
#4950
b110010 "
b110010 *
b110010 +
1!
1#
#4960
b0 $
b0 )
#4980
b1111111111111111 $
b1111111111111111 )
#5000
b0 $
b0 )
0!
0#
#5020
b1111111111111111 $
b1111111111111111 )
#5040
b0 $
b0 )
#5050
b110011 "
b110011 *
b110011 +
1!
1#
#5060
b1111111111111111 $
b1111111111111111 )
#5080
b0 $
b0 )
#5100
b1111111111111111 $
b1111111111111111 )
0!
0#
#5120
b0 $
b0 )
#5140
b1111111111111111 $
b1111111111111111 )
#5150
b110100 "
b110100 *
b110100 +
1!
1#
#5160
b0 $
b0 )
#5180
b1111111111111111 $
b1111111111111111 )
#5200
b0 $
b0 )
0!
0#
#5220
b1111111111111111 $
b1111111111111111 )
#5240
b0 $
b0 )
#5250
b110101 "
b110101 *
b110101 +
1!
1#
#5260
b1111111111111111 $
b1111111111111111 )
#5280
b0 $
b0 )
#5300
b1111111111111111 $
b1111111111111111 )
0!
0#
#5320
b0 $
b0 )
#5340
b1111111111111111 $
b1111111111111111 )
#5350
b110110 "
b110110 *
b110110 +
1!
1#
#5360
b0 $
b0 )
#5380
b1111111111111111 $
b1111111111111111 )
#5400
b0 $
b0 )
0!
0#
#5420
b1111111111111111 $
b1111111111111111 )
#5440
b0 $
b0 )
#5450
b110111 "
b110111 *
b110111 +
1!
1#
#5460
b1111111111111111 $
b1111111111111111 )
#5480
b0 $
b0 )
#5500
b1111111111111111 $
b1111111111111111 )
0!
0#
#5520
b0 $
b0 )
#5540
b1111111111111111 $
b1111111111111111 )
#5550
b111000 "
b111000 *
b111000 +
1!
1#
#5560
b0 $
b0 )
#5580
b1111111111111111 $
b1111111111111111 )
#5600
b0 $
b0 )
0!
0#
#5620
b1111111111111111 $
b1111111111111111 )
#5640
b0 $
b0 )
#5650
b111001 "
b111001 *
b111001 +
1!
1#
#5660
b1111111111111111 $
b1111111111111111 )
#5680
b0 $
b0 )
#5700
b1111111111111111 $
b1111111111111111 )
0!
0#
#5720
b0 $
b0 )
#5740
b1111111111111111 $
b1111111111111111 )
#5750
b111010 "
b111010 *
b111010 +
1!
1#
#5760
b0 $
b0 )
#5780
b1111111111111111 $
b1111111111111111 )
#5800
b0 $
b0 )
0!
0#
#5820
b1111111111111111 $
b1111111111111111 )
#5840
b0 $
b0 )
#5850
b111011 "
b111011 *
b111011 +
1!
1#
#5860
b1111111111111111 $
b1111111111111111 )
#5880
b0 $
b0 )
#5900
b1111111111111111 $
b1111111111111111 )
0!
0#
#5920
b0 $
b0 )
#5940
b1111111111111111 $
b1111111111111111 )
#5950
b111100 "
b111100 *
b111100 +
1!
1#
#5960
b0 $
b0 )
#5980
b1111111111111111 $
b1111111111111111 )
#6000
b0 $
b0 )
0!
0#
#6020
b1111111111111111 $
b1111111111111111 )
#6040
b0 $
b0 )
#6050
b111101 "
b111101 *
b111101 +
1!
1#
#6060
b1111111111111111 $
b1111111111111111 )
#6080
b0 $
b0 )
#6100
b1111111111111111 $
b1111111111111111 )
0!
0#
#6120
b0 $
b0 )
#6140
b1111111111111111 $
b1111111111111111 )
#6150
b111110 "
b111110 *
b111110 +
1!
1#
#6160
b0 $
b0 )
#6180
b1111111111111111 $
b1111111111111111 )
#6200
b0 $
b0 )
0!
0#
#6220
b1111111111111111 $
b1111111111111111 )
#6240
b0 $
b0 )
#6250
b111111 "
b111111 *
b111111 +
1!
1#
#6260
b1111111111111111 $
b1111111111111111 )
#6280
b0 $
b0 )
#6300
b1111111111111111 $
b1111111111111111 )
0!
0#
#6320
b0 $
b0 )
#6340
b1111111111111111 $
b1111111111111111 )
#6350
b1000000 "
b1000000 *
b1000000 +
1!
1#
#6360
b0 $
b0 )
#6380
b1111111111111111 $
b1111111111111111 )
#6400
b0 $
b0 )
0!
0#
#6420
b1111111111111111 $
b1111111111111111 )
#6440
b0 $
b0 )
#6450
b1000001 "
b1000001 *
b1000001 +
1!
1#
#6460
b1111111111111111 $
b1111111111111111 )
#6480
b0 $
b0 )
#6500
b1111111111111111 $
b1111111111111111 )
0!
0#
#6520
b0 $
b0 )
#6540
b1111111111111111 $
b1111111111111111 )
#6550
b1000010 "
b1000010 *
b1000010 +
1!
1#
#6560
b0 $
b0 )
#6580
b1111111111111111 $
b1111111111111111 )
#6600
b0 $
b0 )
0!
0#
#6620
b1111111111111111 $
b1111111111111111 )
#6640
b0 $
b0 )
#6650
b1000011 "
b1000011 *
b1000011 +
1!
1#
#6660
b1111111111111111 $
b1111111111111111 )
#6680
b0 $
b0 )
#6700
b1111111111111111 $
b1111111111111111 )
0!
0#
#6720
b0 $
b0 )
#6740
b1111111111111111 $
b1111111111111111 )
#6750
b1000100 "
b1000100 *
b1000100 +
1!
1#
#6760
b0 $
b0 )
#6780
b1111111111111111 $
b1111111111111111 )
#6800
b0 $
b0 )
0!
0#
#6820
b1111111111111111 $
b1111111111111111 )
#6840
b0 $
b0 )
#6850
b1000101 "
b1000101 *
b1000101 +
1!
1#
#6860
b1111111111111111 $
b1111111111111111 )
#6880
b0 $
b0 )
#6900
b1111111111111111 $
b1111111111111111 )
0!
0#
#6920
b0 $
b0 )
#6940
b1111111111111111 $
b1111111111111111 )
#6950
b1000110 "
b1000110 *
b1000110 +
1!
1#
#6960
b0 $
b0 )
#6980
b1111111111111111 $
b1111111111111111 )
#7000
b0 $
b0 )
0!
0#
#7020
b1111111111111111 $
b1111111111111111 )
#7040
b0 $
b0 )
#7050
b1000111 "
b1000111 *
b1000111 +
1!
1#
#7060
b1111111111111111 $
b1111111111111111 )
#7080
b0 $
b0 )
#7100
b1111111111111111 $
b1111111111111111 )
0!
0#
#7120
b0 $
b0 )
#7140
b1111111111111111 $
b1111111111111111 )
#7150
b1001000 "
b1001000 *
b1001000 +
1!
1#
#7160
b0 $
b0 )
#7180
b1111111111111111 $
b1111111111111111 )
#7200
b0 $
b0 )
0!
0#
#7220
b1111111111111111 $
b1111111111111111 )
#7240
b0 $
b0 )
#7250
b1001001 "
b1001001 *
b1001001 +
1!
1#
#7260
b1111111111111111 $
b1111111111111111 )
#7280
b0 $
b0 )
#7300
b1111111111111111 $
b1111111111111111 )
0!
0#
#7320
b0 $
b0 )
#7340
b1111111111111111 $
b1111111111111111 )
#7350
b1001010 "
b1001010 *
b1001010 +
1!
1#
#7360
b0 $
b0 )
#7380
b1111111111111111 $
b1111111111111111 )
#7400
b0 $
b0 )
0!
0#
#7420
b1111111111111111 $
b1111111111111111 )
#7440
b0 $
b0 )
#7450
b1001011 "
b1001011 *
b1001011 +
1!
1#
#7460
b1111111111111111 $
b1111111111111111 )
#7480
b0 $
b0 )
#7500
b1111111111111111 $
b1111111111111111 )
0!
0#
#7520
b0 $
b0 )
#7540
b1111111111111111 $
b1111111111111111 )
#7550
b1001100 "
b1001100 *
b1001100 +
1!
1#
#7560
b0 $
b0 )
#7580
b1111111111111111 $
b1111111111111111 )
#7600
b0 $
b0 )
0!
0#
#7620
b1111111111111111 $
b1111111111111111 )
#7640
b0 $
b0 )
#7650
b1001101 "
b1001101 *
b1001101 +
1!
1#
#7660
b1111111111111111 $
b1111111111111111 )
#7680
b0 $
b0 )
#7700
b1111111111111111 $
b1111111111111111 )
0!
0#
#7720
b0 $
b0 )
#7740
b1111111111111111 $
b1111111111111111 )
#7750
b1001110 "
b1001110 *
b1001110 +
1!
1#
#7760
b0 $
b0 )
#7780
b1111111111111111 $
b1111111111111111 )
#7800
b0 $
b0 )
0!
0#
#7820
b1111111111111111 $
b1111111111111111 )
#7840
b0 $
b0 )
#7850
b1001111 "
b1001111 *
b1001111 +
1!
1#
#7860
b1111111111111111 $
b1111111111111111 )
#7880
b0 $
b0 )
#7900
b1111111111111111 $
b1111111111111111 )
0!
0#
#7920
b0 $
b0 )
#7940
b1111111111111111 $
b1111111111111111 )
#7950
b1010000 "
b1010000 *
b1010000 +
1!
1#
#7960
b0 $
b0 )
#7980
b1111111111111111 $
b1111111111111111 )
#8000
b0 $
b0 )
0!
0#
#8020
b1111111111111111 $
b1111111111111111 )
#8040
b0 $
b0 )
#8050
b1010001 "
b1010001 *
b1010001 +
1!
1#
#8060
b1111111111111111 $
b1111111111111111 )
#8080
b0 $
b0 )
#8100
b1111111111111111 $
b1111111111111111 )
0!
0#
#8120
b0 $
b0 )
#8140
b1111111111111111 $
b1111111111111111 )
#8150
b1010010 "
b1010010 *
b1010010 +
1!
1#
#8160
b0 $
b0 )
#8180
b1111111111111111 $
b1111111111111111 )
#8200
b0 $
b0 )
0!
0#
#8220
b1111111111111111 $
b1111111111111111 )
#8240
b0 $
b0 )
#8250
b1010011 "
b1010011 *
b1010011 +
1!
1#
#8260
b1111111111111111 $
b1111111111111111 )
#8280
b0 $
b0 )
#8300
b1111111111111111 $
b1111111111111111 )
0!
0#
#8320
b0 $
b0 )
#8340
b1111111111111111 $
b1111111111111111 )
#8350
b1010100 "
b1010100 *
b1010100 +
1!
1#
#8360
b0 $
b0 )
#8380
b1111111111111111 $
b1111111111111111 )
#8400
b0 $
b0 )
0!
0#
#8420
b1111111111111111 $
b1111111111111111 )
#8440
b0 $
b0 )
#8450
b1010101 "
b1010101 *
b1010101 +
1!
1#
#8460
b1111111111111111 $
b1111111111111111 )
#8480
b0 $
b0 )
#8500
b1111111111111111 $
b1111111111111111 )
0!
0#
#8520
b0 $
b0 )
#8540
b1111111111111111 $
b1111111111111111 )
#8550
b1010110 "
b1010110 *
b1010110 +
1!
1#
#8560
b0 $
b0 )
#8580
b1111111111111111 $
b1111111111111111 )
#8600
b0 $
b0 )
0!
0#
#8620
b1111111111111111 $
b1111111111111111 )
#8640
b0 $
b0 )
#8650
b1010111 "
b1010111 *
b1010111 +
1!
1#
#8660
b1111111111111111 $
b1111111111111111 )
#8680
b0 $
b0 )
#8700
b1111111111111111 $
b1111111111111111 )
0!
0#
#8720
b0 $
b0 )
#8740
b1111111111111111 $
b1111111111111111 )
#8750
b1011000 "
b1011000 *
b1011000 +
1!
1#
#8760
b0 $
b0 )
#8780
b1111111111111111 $
b1111111111111111 )
#8800
b0 $
b0 )
0!
0#
#8820
b1111111111111111 $
b1111111111111111 )
#8840
b0 $
b0 )
#8850
b1011001 "
b1011001 *
b1011001 +
1!
1#
#8860
b1111111111111111 $
b1111111111111111 )
#8880
b0 $
b0 )
#8900
b1111111111111111 $
b1111111111111111 )
0!
0#
#8920
b0 $
b0 )
#8940
b1111111111111111 $
b1111111111111111 )
#8950
b1011010 "
b1011010 *
b1011010 +
1!
1#
#8960
b0 $
b0 )
#8980
b1111111111111111 $
b1111111111111111 )
#9000
b0 $
b0 )
0!
0#
#9020
b1111111111111111 $
b1111111111111111 )
#9040
b0 $
b0 )
#9050
b1011011 "
b1011011 *
b1011011 +
1!
1#
#9060
b1111111111111111 $
b1111111111111111 )
#9080
b0 $
b0 )
#9100
b1111111111111111 $
b1111111111111111 )
0!
0#
#9120
b0 $
b0 )
#9140
b1111111111111111 $
b1111111111111111 )
#9150
b1011100 "
b1011100 *
b1011100 +
1!
1#
#9160
b0 $
b0 )
#9180
b1111111111111111 $
b1111111111111111 )
#9200
b0 $
b0 )
0!
0#
#9220
b1111111111111111 $
b1111111111111111 )
#9240
b0 $
b0 )
#9250
b1011101 "
b1011101 *
b1011101 +
1!
1#
#9260
b1111111111111111 $
b1111111111111111 )
#9280
b0 $
b0 )
#9300
b1111111111111111 $
b1111111111111111 )
0!
0#
#9320
b0 $
b0 )
#9340
b1111111111111111 $
b1111111111111111 )
#9350
b1011110 "
b1011110 *
b1011110 +
1!
1#
#9360
b0 $
b0 )
#9380
b1111111111111111 $
b1111111111111111 )
#9400
b0 $
b0 )
0!
0#
#9420
b1111111111111111 $
b1111111111111111 )
#9440
b0 $
b0 )
#9450
b1011111 "
b1011111 *
b1011111 +
1!
1#
#9460
b1111111111111111 $
b1111111111111111 )
#9480
b0 $
b0 )
#9500
b1111111111111111 $
b1111111111111111 )
0!
0#
#9520
b0 $
b0 )
#9540
b1111111111111111 $
b1111111111111111 )
#9550
b1100000 "
b1100000 *
b1100000 +
1!
1#
#9560
b0 $
b0 )
#9580
b1111111111111111 $
b1111111111111111 )
#9600
b0 $
b0 )
0!
0#
#9620
b1111111111111111 $
b1111111111111111 )
#9640
b0 $
b0 )
#9650
b1100001 "
b1100001 *
b1100001 +
1!
1#
#9660
b1111111111111111 $
b1111111111111111 )
#9680
b0 $
b0 )
#9700
b1111111111111111 $
b1111111111111111 )
0!
0#
#9720
b0 $
b0 )
#9740
b1111111111111111 $
b1111111111111111 )
#9750
b1100010 "
b1100010 *
b1100010 +
1!
1#
#9760
b0 $
b0 )
#9780
b1111111111111111 $
b1111111111111111 )
#9800
b0 $
b0 )
0!
0#
#9820
b1111111111111111 $
b1111111111111111 )
#9840
b0 $
b0 )
#9850
b1100011 "
b1100011 *
b1100011 +
1!
1#
#9860
b1111111111111111 $
b1111111111111111 )
#9880
b0 $
b0 )
#9900
b1111111111111111 $
b1111111111111111 )
0!
0#
#9920
b0 $
b0 )
#9940
b1111111111111111 $
b1111111111111111 )
#9950
b1100100 "
b1100100 *
b1100100 +
1!
1#
#9960
b0 $
b0 )
#9980
b1111111111111111 $
b1111111111111111 )
#10000
b0 $
b0 )
0!
0#
#10020
b1111111111111111 $
b1111111111111111 )
#10040
b0 $
b0 )
#10050
b1100101 "
b1100101 *
b1100101 +
1!
1#
#10060
b1111111111111111 $
b1111111111111111 )
#10080
b0 $
b0 )
#10100
b1111111111111111 $
b1111111111111111 )
0!
0#
#10120
b0 $
b0 )
#10140
b1111111111111111 $
b1111111111111111 )
#10150
b1100110 "
b1100110 *
b1100110 +
1!
1#
#10160
b0 $
b0 )
#10180
b1111111111111111 $
b1111111111111111 )
#10200
b0 $
b0 )
0!
0#
#10220
b1111111111111111 $
b1111111111111111 )
#10240
b0 $
b0 )
#10250
b1100111 "
b1100111 *
b1100111 +
1!
1#
#10260
b1111111111111111 $
b1111111111111111 )
#10280
b0 $
b0 )
#10300
b1111111111111111 $
b1111111111111111 )
0!
0#
#10320
b0 $
b0 )
#10340
b1111111111111111 $
b1111111111111111 )
#10350
b1101000 "
b1101000 *
b1101000 +
1!
1#
#10360
b0 $
b0 )
#10380
b1111111111111111 $
b1111111111111111 )
#10400
b0 $
b0 )
0!
0#
#10420
b1111111111111111 $
b1111111111111111 )
#10440
b0 $
b0 )
#10450
b1101001 "
b1101001 *
b1101001 +
1!
1#
#10460
b1111111111111111 $
b1111111111111111 )
#10480
b0 $
b0 )
#10500
b1111111111111111 $
b1111111111111111 )
0!
0#
#10520
b0 $
b0 )
#10540
b1111111111111111 $
b1111111111111111 )
#10550
b1101010 "
b1101010 *
b1101010 +
1!
1#
#10560
b0 $
b0 )
#10580
b1111111111111111 $
b1111111111111111 )
#10600
b0 $
b0 )
0!
0#
#10620
b1111111111111111 $
b1111111111111111 )
#10640
b0 $
b0 )
#10650
b1101011 "
b1101011 *
b1101011 +
1!
1#
