16bit-computer/memory/register.v
// 1 and 16 bit memory devices that resemble a D-Flip Flop. 

module REGISTER (
  input clk,
  input reset_n,
  input load, 
  input d_in, 
  output d_out
);

  reg bit_data; 

  always @(posedge clk) begin
    if (!reset_n) begin
      bit_data <= 0; 
    end else if(load) begin
      bit_data <= d_in; 
    end
  end
  
  assign d_out = bit_data; 
endmodule

module REGISTER_16(
  input clk,
  input reset_n,
  input load, 
  input [15:0] d_in, 
  output [15:0] d_out
);

  reg [15:0] bit_data; 

  always @(posedge clk) begin
    if (!reset_n) begin
      bit_data <= {16{1'b0}}; 
    end else if(load) begin
      bit_data <= d_in; 
    end
  end
  
  assign d_out = bit_data; 
endmodule

16bit-computer/memory/register_tb.v
// 1 bit and 16 bit memory test benches. 

`timescale 1ns/100ps // define the minimum time unit used by the simulation

module ram_tb;
    reg _clk=0; 
    wire clk; 
    reg reset_n = 1; // set to 0 to send a reset (pull down like in real hardware)
    reg load = 1; 
    realtime capture = 0.0;

    always #5 _clk=~_clk; // invert clock every 5 ns
    assign clk = _clk; 

    reg data_in = 0; 
    wire data_out; 
    REGISTER register_1bit(clk, reset_n, load, data_in, data_out); 

    reg [15:0] data_in16 = {16{1'b0}}; 
    wire [15:0] data_out16; 
    REGISTER_16 register_16(clk, reset_n, load, data_in16, data_out16); 

    initial begin
        forever begin
            #2; 
            data_in = ~data_in; 
            data_in16 = ~data_in16; 
            // capture = $realtime;
            // $display("%t", capture); // uncomment to print the cycle count of the simulation in realtime.
        end
    end

    initial begin
        $display("REGISTER TESTBENCH"); 
        $dumpfile("register-dump.vcd");
        $dumpvars(3);
        #100000 // run simulation for 100000 timeunits (in this case 100000 ns as defined on top)
        $finish;
    end 

endmodule

hardware/memory/register-dump.vcd
$date
	Thu May  2 15:43:48 2024
$end
$version
	Icarus Verilog
$end
$timescale
	100ps
$end
$scope module ram_tb $end
$var wire 1 ! clk $end
$var wire 16 " data_out16 [15:0] $end
$var wire 1 # data_out $end
$var reg 1 $ _clk $end
$var reg 1 % data_in $end
$var reg 16 & data_in16 [15:0] $end
$var reg 1 ' load $end
$var reg 1 ( reset_n $end
$var real 1 ) capture $end
$scope module register_16 $end
$var wire 1 ! clk $end
$var wire 16 * d_in [15:0] $end
$var wire 16 + d_out [15:0] $end
$var wire 1 ' load $end
$var wire 1 ( reset_n $end
$var reg 16 , bit_data [15:0] $end
$upscope $end
$scope module register_1bit $end
$var wire 1 ! clk $end
$var wire 1 % d_in $end
$var wire 1 # d_out $end
$var wire 1 ' load $end
$var wire 1 ( reset_n $end
$var reg 1 - bit_data $end
$upscope $end
$upscope $end
$enddefinitions $end
$comment Show the parameter values. $end
$dumpall
$end
#0
$dumpvars
x-
bx ,
bx +
b0 *
r0 )
1(
1'
b0 &
0%
0$
x#
bx "
0!
$end
#20
b1111111111111111 &
b1111111111111111 *
1%
#40
b0 &
b0 *
0%
#50
0#
0-
b0 "
b0 +
b0 ,
1!
1$
#60
b1111111111111111 &
b1111111111111111 *
1%
#80
b0 &
b0 *
0%
#100
b1111111111111111 &
b1111111111111111 *
1%
0!
0$
#120
b0 &
b0 *
0%
#140
b1111111111111111 &
b1111111111111111 *
1%
#150
b1111111111111111 "
b1111111111111111 +
b1111111111111111 ,
1#
1-
1!
1$
#160
b0 &
b0 *
0%
#180
b1111111111111111 &
b1111111111111111 *
1%
#200
b0 &
b0 *
0%
0!
0$
#220
b1111111111111111 &
b1111111111111111 *
1%
#240
b0 &
b0 *
0%
#250
0#
0-
b0 "
b0 +
b0 ,
1!
1$
#260
b1111111111111111 &
b1111111111111111 *
1%
#280
b0 &
b0 *
0%
#300
b1111111111111111 &
b1111111111111111 *
1%
0!
0$
#320
b0 &
b0 *
0%
#340
b1111111111111111 &
b1111111111111111 *
1%
#350
b1111111111111111 "
b1111111111111111 +
b1111111111111111 ,
1#
1-
1!
1$
#360
b0 &
b0 *
0%
#380
b1111111111111111 &
b1111111111111111 *
1%
#400
b0 &
b0 *
0%
0!
0$
#420
b1111111111111111 &
b1111111111111111 *
1%
#440
b0 &
b0 *
0%
#450
0#
0-
b0 "
b0 +
b0 ,
1!
1$
#460
b1111111111111111 &
b1111111111111111 *
1%
#480
b0 &
b0 *
0%
#500
b1111111111111111 &
b1111111111111111 *
1%
0!
0$
#520
b0 &
b0 *
0%
#540
b1111111111111111 &
b1111111111111111 *
1%
#550
b1111111111111111 "
b1111111111111111 +
b1111111111111111 ,
1#
1-
1!
1$
#560
b0 &
b0 *
0%
#580
b1111111111111111 &
b1111111111111111 *
1%
#600
b0 &
b0 *
0%
0!
0$
#620
b1111111111111111 &
b1111111111111111 *
1%
#640
b0 &
b0 *
0%
#650
0#
0-
b0 "
b0 +
b0 ,
1!
1$
#660
b1111111111111111 &
b1111111111111111 *
1%
#680
b0 &
b0 *
0%
#700
b1111111111111111 &
b1111111111111111 *
1%
0!
0$
#720
b0 &
b0 *
0%
#740
b1111111111111111 &
b1111111111111111 *
1%
#750
b1111111111111111 "
b1111111111111111 +
b1111111111111111 ,
1#
1-
1!
1$
#760
b0 &
b0 *
0%
#780
b1111111111111111 &
b1111111111111111 *
1%
#800
b0 &
b0 *
0%
0!
0$
#820
b1111111111111111 &
b1111111111111111 *
1%
#840
b0 &
b0 *
0%
#850
0#
0-
b0 "
b0 +
b0 ,
1!
1$
#860
b1111111111111111 &
b1111111111111111 *
1%
#880
b0 &
b0 *
0%
#900
b1111111111111111 &
b1111111111111111 *
1%
0!
0$
#920
b0 &
b0 *
0%
#940
b1111111111111111 &
b1111111111111111 *
1%
#950
b1111111111111111 "
b1111111111111111 +
b1111111111111111 ,
1#
1-
1!
1$
#960
b0 &
b0 *
0%
#980
b1111111111111111 &
b1111111111111111 *
1%
#1000
b0 &
b0 *
0%
0!
0$
#1020
b1111111111111111 &
b1111111111111111 *
1%
#1040
b0 &
b0 *
0%
#1050
0#
0-
b0 "
b0 +
b0 ,
1!
1$
#1060
b1111111111111111 &
b1111111111111111 *
1%
#1080
b0 &
b0 *
0%
#1100
b1111111111111111 &
b1111111111111111 *
1%
0!
0$
#1120
b0 &
b0 *
0%
#1140
b1111111111111111 &
b1111111111111111 *
1%
#1150
b1111111111111111 "
b1111111111111111 +
b1111111111111111 ,
1#
1-
1!
1$
#1160
b0 &
b0 *
0%
#1180
b1111111111111111 &
b1111111111111111 *
1%
#1200
b0 &
b0 *
0%
0!
0$
#1220
b1111111111111111 &
b1111111111111111 *
1%
#1240
b0 &
b0 *
0%
#1250
0#
0-
b0 "
b0 +
b0 ,
1!
1$
#1260
b1111111111111111 &
b1111111111111111 *
1%
#1280
b0 &
b0 *
0%
#1300
b1111111111111111 &
b1111111111111111 *
1%
0!
0$
#1320
b0 &
b0 *
0%
#1340
b1111111111111111 &
b1111111111111111 *
1%
#1350
b1111111111111111 "
b1111111111111111 +
b1111111111111111 ,
1#
1-
1!
1$
#1360
b0 &
b0 *
0%
#1380
b1111111111111111 &
b1111111111111111 *
1%
#1400
b0 &
b0 *
0%
0!
0$
#1420
b1111111111111111 &
b1111111111111111 *
1%
#1440
b0 &
b0 *
0%
#1450
0#
0-
b0 "
b0 +
b0 ,
1!
1$
#1460
b1111111111111111 &
b1111111111111111 *
1%
#1480
b0 &
b0 *
0%
#1500
b1111111111111111 &
b1111111111111111 *
1%
0!
0$
#1520
b0 &
b0 *
0%
#1540
b1111111111111111 &
b1111111111111111 *
1%
#1550
b1111111111111111 "
b1111111111111111 +
b1111111111111111 ,
1#
1-
1!
1$
#1560
b0 &
b0 *
0%
#1580
b1111111111111111 &
b1111111111111111 *
1%
#1600
b0 &
b0 *
0%
0!
0$
#1620
b1111111111111111 &
b1111111111111111 *
1%
#1640
b0 &
b0 *
0%
#1650
0#
0-
b0 "
b0 +
b0 ,
1!
1$
#1660
b1111111111111111 &
b1111111111111111 *
1%
#1680
b0 &
b0 *
0%
#1700
b1111111111111111 &
b1111111111111111 *
1%
0!
0$
#1720
b0 &
b0 *
0%
#1740
b1111111111111111 &
b1111111111111111 *
1%
#1750
b1111111111111111 "
b1111111111111111 +
b1111111111111111 ,
1#
1-
1!
1$
#1760
b0 &
b0 *
0%
#1780
b1111111111111111 &
b1111111111111111 *
1%
#1800
b0 &
b0 *
0%
0!
0$
#1820
b1111111111111111 &
b1111111111111111 *
1%
#1840
b0 &
b0 *
0%
#1850
0#
0-
b0 "
b0 +
b0 ,
1!
1$
#1860
b1111111111111111 &
b1111111111111111 *
1%
#1880
b0 &
b0 *
0%
#1900
b1111111111111111 &
b1111111111111111 *
1%
0!
0$
#1920
b0 &
b0 *
0%
#1940
b1111111111111111 &
b1111111111111111 *
1%
#1950
b1111111111111111 "
b1111111111111111 +
b1111111111111111 ,
1#
1-
1!
1$
#1960
b0 &
b0 *
0%
#1980
b1111111111111111 &
b1111111111111111 *
1%
#2000
b0 &
b0 *
0%
0!
0$
#2020
b1111111111111111 &
b1111111111111111 *
1%
#2040
b0 &
b0 *
0%
#2050
0#
0-
b0 "
b0 +
b0 ,
1!
1$
#2060
b1111111111111111 &
b1111111111111111 *
1%
#2080
b0 &
b0 *
0%
#2100
b1111111111111111 &
b1111111111111111 *
1%
0!
0$
#2120
b0 &
b0 *
0%
#2140
b1111111111111111 &
b1111111111111111 *
1%
#2150
b1111111111111111 "
b1111111111111111 +
b1111111111111111 ,
1#
1-
1!
1$
#2160
b0 &
b0 *
0%
#2180
b1111111111111111 &
b1111111111111111 *
1%
#2200
b0 &
b0 *
0%
0!
0$
#2220
b1111111111111111 &
b1111111111111111 *
1%
#2240
b0 &
b0 *
0%
#2250
0#
0-
b0 "
b0 +
b0 ,
1!
1$
#2260
b1111111111111111 &
b1111111111111111 *
1%
#2280
b0 &
b0 *
0%
#2300
b1111111111111111 &
b1111111111111111 *
1%
0!
0$
#2320
b0 &
b0 *
0%
#2340
b1111111111111111 &
b1111111111111111 *
1%
#2350
b1111111111111111 "
b1111111111111111 +
b1111111111111111 ,
1#
1-
1!
1$
#2360
b0 &
b0 *
0%
#2380
b1111111111111111 &
b1111111111111111 *
1%
#2400
b0 &
b0 *
0%
0!
0$
#2420
b1111111111111111 &
b1111111111111111 *
1%
#2440
b0 &
b0 *
0%
#2450
0#
0-
b0 "
b0 +
b0 ,
1!
1$
#2460
b1111111111111111 &
b1111111111111111 *
1%
#2480
b0 &
b0 *
0%
#2500
b1111111111111111 &
b1111111111111111 *
1%
0!
0$
#2520
b0 &
b0 *
0%
#2540
b1111111111111111 &
b1111111111111111 *
1%
#2550
b1111111111111111 "
b1111111111111111 +
b1111111111111111 ,
1#
1-
1!
1$
#2560
b0 &
b0 *
0%
#2580
b1111111111111111 &
b1111111111111111 *
1%
#2600
b0 &
b0 *
0%
0!
0$
#2620
b1111111111111111 &
b1111111111111111 *
1%
#2640
b0 &
b0 *
0%
#2650
0#
0-
b0 "
b0 +
b0 ,
1!
1$
#2660
b1111111111111111 &
b1111111111111111 *
1%
#2680
b0 &
b0 *
0%
#2700
b1111111111111111 &
b1111111111111111 *
1%
0!
0$
#2720
b0 &
b0 *
0%
#2740
b1111111111111111 &
b1111111111111111 *
1%
#2750
b1111111111111111 "
b1111111111111111 +
b1111111111111111 ,
1#
1-
1!
1$
#2760
b0 &
b0 *
0%
#2780
b1111111111111111 &
b1111111111111111 *
1%
#2800
b0 &
b0 *
0%
0!
0$
#2820
b1111111111111111 &
b1111111111111111 *
1%
#2840
b0 &
b0 *
0%
#2850
0#
0-
b0 "
b0 +
b0 ,
1!
1$
#2860
b1111111111111111 &
b1111111111111111 *
1%
#2880
b0 &
b0 *
0%
#2900
b1111111111111111 &
b1111111111111111 *
1%
0!
0$
#2920
b0 &
b0 *
0%
#2940
b1111111111111111 &
b1111111111111111 *
1%
#2950
b1111111111111111 "
b1111111111111111 +
b1111111111111111 ,
1#
1-
1!
1$
#2960
b0 &
b0 *
0%
#2980
b1111111111111111 &
b1111111111111111 *
1%
#3000
b0 &
b0 *
0%
0!
0$
#3020
b1111111111111111 &
b1111111111111111 *
1%
#3040
b0 &
b0 *
0%
#3050
0#
0-
b0 "
b0 +
b0 ,
1!
1$
#3060
b1111111111111111 &
b1111111111111111 *
1%
#3080
b0 &
b0 *
0%
#3100
b1111111111111111 &
b1111111111111111 *
1%
0!
0$
#3120
b0 &
b0 *
0%
#3140
b1111111111111111 &
b1111111111111111 *
1%
#3150
b1111111111111111 "
b1111111111111111 +
b1111111111111111 ,
1#
1-
1!
1$
#3160
b0 &
b0 *
0%
#3180
b1111111111111111 &
b1111111111111111 *
1%
#3200
b0 &
b0 *
0%
0!
0$
#3220
b1111111111111111 &
b1111111111111111 *
1%
#3240
b0 &
b0 *
0%
#3250
0#
0-
b0 "
b0 +
b0 ,
1!
1$
#3260
b1111111111111111 &
b1111111111111111 *
1%
#3280
b0 &
b0 *
0%
#3300
b1111111111111111 &
b1111111111111111 *
1%
0!
0$
#3320
b0 &
b0 *
0%
#3340
b1111111111111111 &
b1111111111111111 *
1%
#3350
b1111111111111111 "
b1111111111111111 +
b1111111111111111 ,
1#
1-
1!
1$
#3360
b0 &
b0 *
0%
#3380
b1111111111111111 &
b1111111111111111 *
1%
#3400
b0 &
b0 *
0%
0!
0$
#3420
b1111111111111111 &
b1111111111111111 *
1%
#3440
b0 &
b0 *
0%
#3450
0#
0-
b0 "
b0 +
b0 ,
1!
1$
#3460
b1111111111111111 &
b1111111111111111 *
1%
#3480
b0 &
b0 *
0%
#3500
b1111111111111111 &
b1111111111111111 *
1%
0!
0$
#3520
b0 &
b0 *
0%
#3540
b1111111111111111 &
b1111111111111111 *
1%
#3550
b1111111111111111 "
b1111111111111111 +
b1111111111111111 ,
1#
1-
1!
1$
#3560
b0 &
b0 *
0%
#3580
b1111111111111111 &
b1111111111111111 *
1%
#3600
b0 &
b0 *
0%
0!
0$
#3620
b1111111111111111 &
b1111111111111111 *
1%
#3640
b0 &
b0 *
0%
#3650
0#
0-
b0 "
b0 +
b0 ,
1!
1$
#3660
b1111111111111111 &
b1111111111111111 *
1%
#3680
b0 &
b0 *
0%
#3700
b1111111111111111 &
b1111111111111111 *
1%
0!
0$
#3720
b0 &
b0 *
0%
#3740
b1111111111111111 &
b1111111111111111 *
1%
#3750
b1111111111111111 "
b1111111111111111 +
b1111111111111111 ,
1#
1-
1!
1$
#3760
b0 &
b0 *
0%
#3780
b1111111111111111 &
b1111111111111111 *
1%
#3800
b0 &
b0 *
0%
0!
0$
#3820
b1111111111111111 &
b1111111111111111 *
1%
#3840
b0 &
b0 *
0%
#3850
0#
0-
b0 "
b0 +
b0 ,
1!
1$
#3860
b1111111111111111 &
b1111111111111111 *
1%
#3880
b0 &
b0 *
0%
#3900
b1111111111111111 &
b1111111111111111 *
1%
0!
0$
#3920
b0 &
b0 *
0%
#3940
b1111111111111111 &
b1111111111111111 *
1%
#3950
b1111111111111111 "
b1111111111111111 +
b1111111111111111 ,
1#
1-
1!
1$
#3960
b0 &
b0 *
0%
#3980
b1111111111111111 &
b1111111111111111 *
1%
#4000
b0 &
b0 *
0%
0!
0$
#4020
b1111111111111111 &
b1111111111111111 *
1%
#4040
b0 &
b0 *
0%
#4050
0#
0-
b0 "
b0 +
b0 ,
1!
1$
#4060
b1111111111111111 &
b1111111111111111 *
1%
#4080
b0 &
b0 *
0%
#4100
b1111111111111111 &
b1111111111111111 *
1%
0!
0$
#4120
b0 &
b0 *
0%
#4140
b1111111111111111 &
b1111111111111111 *
1%
#4150
b1111111111111111 "
b1111111111111111 +
b1111111111111111 ,
1#
1-
1!
1$
#4160
b0 &
b0 *
0%
#4180
b1111111111111111 &
b1111111111111111 *
1%
#4200
b0 &
b0 *
0%
0!
0$
#4220
b1111111111111111 &
b1111111111111111 *
1%
#4240
b0 &
b0 *
0%
#4250
0#
0-
b0 "
b0 +
b0 ,
1!
1$
#4260
b1111111111111111 &
b1111111111111111 *
1%
#4280
b0 &
b0 *
0%
#4300
b1111111111111111 &
b1111111111111111 *
1%
0!
0$
#4320
b0 &
b0 *
0%
#4340
b1111111111111111 &
b1111111111111111 *
1%
#4350
b1111111111111111 "
b1111111111111111 +
b1111111111111111 ,
1#
1-
1!
1$
#4360
b0 &
b0 *
0%
#4380
b1111111111111111 &
b1111111111111111 *
1%
#4400
b0 &
b0 *
0%
0!
0$
#4420
b1111111111111111 &
b1111111111111111 *
1%
#4440
b0 &
b0 *
0%
#4450
0#
0-
b0 "
b0 +
b0 ,
1!
1$
#4460
b1111111111111111 &
b1111111111111111 *
1%
#4480
b0 &
b0 *
0%
#4500
b1111111111111111 &
b1111111111111111 *
1%
0!
0$
#4520
b0 &
b0 *
0%
#4540
b1111111111111111 &
b1111111111111111 *
1%
#4550
b1111111111111111 "
b1111111111111111 +
b1111111111111111 ,
1#
1-
1!
1$
#4560
b0 &
b0 *
0%
#4580
b1111111111111111 &
b1111111111111111 *
1%
#4600
b0 &
b0 *
0%
0!
0$
#4620
b1111111111111111 &
b1111111111111111 *
1%
#4640
b0 &
b0 *
0%
#4650
0#
0-
b0 "
b0 +
b0 ,
1!
1$
#4660
b1111111111111111 &
b1111111111111111 *
1%
#4680
b0 &
b0 *
0%
#4700
b1111111111111111 &
b1111111111111111 *
1%
0!
0$
#4720
b0 &
b0 *
0%
#4740
b1111111111111111 &
b1111111111111111 *
1%
#4750
b1111111111111111 "
b1111111111111111 +
b1111111111111111 ,
1#
1-
1!
1$
#4760
b0 &
b0 *
0%
#4780
b1111111111111111 &
b1111111111111111 *
1%
#4800
b0 &
b0 *
0%
0!
0$
#4820
b1111111111111111 &
b1111111111111111 *
1%
#4840
b0 &
b0 *
0%
#4850
0#
0-
b0 "
b0 +
b0 ,
1!
1$
#4860
b1111111111111111 &
b1111111111111111 *
1%
#4880
b0 &
b0 *
0%
#4900
b1111111111111111 &
b1111111111111111 *
1%
0!
0$
#4920
b0 &
b0 *
0%
#4940
b1111111111111111 &
b1111111111111111 *
1%
#4950
b1111111111111111 "
b1111111111111111 +
b1111111111111111 ,
1#
1-
1!
1$
#4960
b0 &
b0 *
0%
#4980
b1111111111111111 &
b1111111111111111 *
1%
#5000
b0 &
b0 *
0%
0!
0$
#5020
b1111111111111111 &
b1111111111111111 *
1%
#5040
b0 &
b0 *
0%
#5050
0#
0-
b0 "
b0 +
b0 ,
1!
1$
#5060
b1111111111111111 &
b1111111111111111 *
1%
#5080
b0 &
b0 *
0%
#5100
b1111111111111111 &
b1111111111111111 *
1%
0!
0$
#5120
b0 &
b0 *
0%
#5140
b1111111111111111 &
b1111111111111111 *
1%
#5150
b1111111111111111 "
b1111111111111111 +
b1111111111111111 ,
1#
1-
1!
1$
#5160
b0 &
b0 *
0%
#5180
b1111111111111111 &
b1111111111111111 *
1%
#5200
b0 &
b0 *
0%
0!
0$
#5220
b1111111111111111 &
b1111111111111111 *
1%
#5240
b0 &
b0 *
0%
#5250
0#
0-
b0 "
b0 +
b0 ,
1!
1$
#5260
b1111111111111111 &
b1111111111111111 *
1%
#5280
b0 &
b0 *
0%
#5300
b1111111111111111 &
b1111111111111111 *
1%
0!
0$
#5320
b0 &
b0 *
0%
#5340
b1111111111111111 &
b1111111111111111 *
1%
#5350
b1111111111111111 "
b1111111111111111 +
b1111111111111111 ,
1#
1-
1!
1$
#5360
b0 &
b0 *
0%
#5380
b1111111111111111 &
b1111111111111111 *
1%
#5400
b0 &
b0 *
0%
0!
0$
#5420
b1111111111111111 &
b1111111111111111 *
1%
#5440
b0 &
b0 *
0%
#5450
0#
0-
b0 "
b0 +
b0 ,
1!
1$
#5460
b1111111111111111 &
b1111111111111111 *
1%
#5480
b0 &
b0 *
0%
#5500
b1111111111111111 &
b1111111111111111 *
1%
0!
0$
#5520
b0 &
b0 *
0%
#5540
b1111111111111111 &
b1111111111111111 *
1%
#5550
b1111111111111111 "
b1111111111111111 +
b1111111111111111 ,
1#
1-
1!
1$
#5560
b0 &
b0 *
0%
#5580
b1111111111111111 &
b1111111111111111 *
1%
#5600
b0 &
b0 *
0%
0!
0$
#5620
b1111111111111111 &
b1111111111111111 *
1%
#5640
b0 &
b0 *
0%
#5650
0#
0-
b0 "
b0 +
b0 ,
1!
1$
#5660
b1111111111111111 &
b1111111111111111 *
1%
#5680
b0 &
b0 *
0%
#5700
b1111111111111111 &
b1111111111111111 *
1%
0!
0$
#5720
b0 &
b0 *
0%
#5740
b1111111111111111 &
b1111111111111111 *
1%
#5750
b1111111111111111 "
b1111111111111111 +
b1111111111111111 ,
1#
1-
1!
1$
#5760
b0 &
b0 *
0%
#5780
b1111111111111111 &
b1111111111111111 *
1%
#5800
b0 &
b0 *
0%
0!
0$
#5820
b1111111111111111 &
b1111111111111111 *
1%
#5840
b0 &
b0 *
0%
#5850
0#
0-
b0 "
b0 +
b0 ,
1!
1$
#5860
b1111111111111111 &
b1111111111111111 *
1%
#5880
b0 &
b0 *
0%
#5900
b1111111111111111 &
b1111111111111111 *
1%
0!
0$
#5920
b0 &
b0 *
0%
#5940
b1111111111111111 &
b1111111111111111 *
1%
#5950
b1111111111111111 "
b1111111111111111 +
b1111111111111111 ,
1#
1-
1!
1$
#5960
b0 &
b0 *
0%
#5980
b1111111111111111 &
b1111111111111111 *
1%
#6000
b0 &
b0 *
0%
0!
0$
#6020
b1111111111111111 &
b1111111111111111 *
1%
#6040
b0 &
b0 *
0%
#6050
0#
0-
b0 "
b0 +
b0 ,
1!
1$
#6060
b1111111111111111 &
b1111111111111111 *
1%
#6080
b0 &
b0 *
0%
#6100
b1111111111111111 &
b1111111111111111 *
1%
0!
0$
#6120
b0 &
b0 *
0%
#6140
b1111111111111111 &
b1111111111111111 *
1%
#6150
b1111111111111111 "
b1111111111111111 +
b1111111111111111 ,
1#
1-
1!
1$
#6160
b0 &
b0 *
0%
#6180
b1111111111111111 &
b1111111111111111 *
1%
#6200
b0 &
b0 *
0%
0!
0$
#6220
b1111111111111111 &
b1111111111111111 *
1%
#6240
b0 &
b0 *
0%
#6250
0#
0-
b0 "
b0 +
b0 ,
1!
1$
#6260
b1111111111111111 &
b1111111111111111 *
1%
#6280
b0 &
b0 *
0%
#6300
b1111111111111111 &
b1111111111111111 *
1%
0!
0$
#6320
b0 &
b0 *
0%
#6340
b1111111111111111 &
b1111111111111111 *
1%
#6350
b1111111111111111 "
b1111111111111111 +
b1111111111111111 ,
1#
1-
1!
1$
#6360
b0 &
b0 *
0%
#6380
b1111111111111111 &
b1111111111111111 *
1%
#6400
b0 &
b0 *
0%
0!
0$
#6420
b1111111111111111 &
b1111111111111111 *
1%
#6440
b0 &
b0 *
0%
#6450
0#
0-
b0 "
b0 +
b0 ,
1!
1$
#6460
b1111111111111111 &
b1111111111111111 *
1%
#6480
b0 &
b0 *
0%
#6500
b1111111111111111 &
b1111111111111111 *
1%
0!
0$
#6520
b0 &
b0 *
0%
#6540
b1111111111111111 &
b1111111111111111 *
1%
#6550
b1111111111111111 "
b1111111111111111 +
b1111111111111111 ,
1#
1-
1!
1$
#6560
b0 &
b0 *
0%
#6580
b1111111111111111 &
b1111111111111111 *
1%
#6600
b0 &
b0 *
0%
0!
0$
#6620
b1111111111111111 &
b1111111111111111 *
1%
#6640
b0 &
b0 *
0%
#6650
0#
0-
b0 "
b0 +
b0 ,
1!
1$
#6660
b1111111111111111 &
b1111111111111111 *
1%
#6680
b0 &
b0 *
0%
#6700
b1111111111111111 &
b1111111111111111 *
1%
0!
0$
#6720
b0 &
b0 *
0%
#6740
b1111111111111111 &
b1111111111111111 *
1%
#6750
b1111111111111111 "
b1111111111111111 +
b1111111111111111 ,
1#
1-
1!
1$
#6760
b0 &
b0 *
0%
#6780
b1111111111111111 &
b1111111111111111 *
1%
#6800
b0 &
b0 *
0%
0!
0$
#6820
b1111111111111111 &
b1111111111111111 *
1%
#6840
b0 &
b0 *
0%
#6850
0#
0-
b0 "
b0 +
b0 ,
1!
1$
#6860
b1111111111111111 &
b1111111111111111 *
1%
#6880
b0 &
b0 *
0%
#6900
b1111111111111111 &
b1111111111111111 *
1%
0!
0$
#6920
b0 &
b0 *
0%
#6940
b1111111111111111 &
b1111111111111111 *
1%
#6950
b1111111111111111 "
b1111111111111111 +
b1111111111111111 ,
1#
1-
1!
1$
#6960
b0 &
b0 *
0%
#6980
b1111111111111111 &
b1111111111111111 *
1%
#7000
b0 &
b0 *
0%
0!
0$
#7020
b1111111111111111 &
b1111111111111111 *
1%
#7040
b0 &
b0 *
0%
#7050
0#
0-
b0 "
b0 +
b0 ,
1!
1$
#7060
b1111111111111111 &
b1111111111111111 *
1%
#7080
b0 &
b0 *
0%
#7100
b1111111111111111 &
b1111111111111111 *
1%
0!
0$
#7120
b0 &
b0 *
0%
#7140
b1111111111111111 &
b1111111111111111 *
1%
#7150
b1111111111111111 "
b1111111111111111 +
b1111111111111111 ,
1#
1-
1!
1$
#7160
b0 &
b0 *
0%
#7180
b1111111111111111 &
b1111111111111111 *
1%
#7200
b0 &
b0 *
0%
0!
0$
#7220
b1111111111111111 &
b1111111111111111 *
1%
#7240
b0 &
b0 *
0%
#7250
0#
0-
b0 "
b0 +
b0 ,
1!
1$
#7260
b1111111111111111 &
b1111111111111111 *
1%
#7280
b0 &
b0 *
0%
#7300
b1111111111111111 &
b1111111111111111 *
1%
0!
0$
#7320
b0 &
b0 *
0%
#7340
b1111111111111111 &
b1111111111111111 *
1%
#7350
b1111111111111111 "
b1111111111111111 +
b1111111111111111 ,
1#
1-
1!
1$
#7360
b0 &
b0 *
0%
#7380
b1111111111111111 &
b1111111111111111 *
1%
#7400
b0 &
b0 *
0%
0!
0$
#7420
b1111111111111111 &
b1111111111111111 *
1%
#7440
b0 &
b0 *
0%
#7450
0#
0-
b0 "
b0 +
b0 ,
1!
1$
#7460
b1111111111111111 &
b1111111111111111 *
1%
#7480
b0 &
b0 *
0%
#7500
b1111111111111111 &
b1111111111111111 *
1%
0!
0$
#7520
b0 &
b0 *
0%
#7540
b1111111111111111 &
b1111111111111111 *
1%
#7550
b1111111111111111 "
b1111111111111111 +
b1111111111111111 ,
1#
1-
1!
1$
#7560
b0 &
b0 *
0%
#7580
b1111111111111111 &
b1111111111111111 *
1%
#7600
b0 &
b0 *
0%
0!
0$
#7620
b1111111111111111 &
b1111111111111111 *
1%
#7640
b0 &
b0 *
0%
#7650
0#
0-
b0 "
b0 +
b0 ,
1!
1$
#7660
b1111111111111111 &
b1111111111111111 *
1%
#7680
b0 &
b0 *
0%
#7700
b1111111111111111 &
b1111111111111111 *
1%
0!
0$
#7720
b0 &
b0 *
0%
#7740
b1111111111111111 &
b1111111111111111 *
1%
#7750
b1111111111111111 "
b1111111111111111 +
b1111111111111111 ,
1#
1-
1!
1$
#7760
b0 &
b0 *
0%
#7780
b1111111111111111 &
b1111111111111111 *
1%
#7800
b0 &
b0 *
0%
0!
0$
#7820
b1111111111111111 &
b1111111111111111 *
1%
#7840
b0 &
b0 *
0%
#7850
0#
0-
b0 "
b0 +
b0 ,
1!
1$
#7860
b1111111111111111 &
b1111111111111111 *
1%
#7880
b0 &
b0 *
0%
#7900
b1111111111111111 &
b1111111111111111 *
1%
0!
0$
#7920
b0 &
b0 *
0%
#7940
b1111111111111111 &
b1111111111111111 *
1%
#7950
b1111111111111111 "
b1111111111111111 +
b1111111111111111 ,
1#
1-
1!
1$
#7960
b0 &
b0 *
0%
#7980
b1111111111111111 &
b1111111111111111 *
1%
#8000
b0 &
b0 *
0%
0!
0$
#8020
b1111111111111111 &
b1111111111111111 *
1%
#8040
b0 &
b0 *
0%
#8050
0#
0-
b0 "
b0 +
b0 ,
1!
1$
#8060
b1111111111111111 &
b1111111111111111 *
1%
#8080
b0 &
b0 *
0%
#8100
b1111111111111111 &
b1111111111111111 *
1%
0!
0$
#8120
b0 &
b0 *
0%
#8140
b1111111111111111 &
b1111111111111111 *
1%
#8150
b1111111111111111 "
b1111111111111111 +
b1111111111111111 ,
1#
1-
1!
1$
#8160
b0 &
b0 *
0%
#8180
b1111111111111111 &
b1111111111111111 *
1%
#8200
b0 &
b0 *
0%
0!
0$
#8220
b1111111111111111 &
b1111111111111111 *
1%
#8240
b0 &
b0 *
0%
#8250
0#
0-
b0 "
b0 +
b0 ,
1!
1$
#8260
b1111111111111111 &
b1111111111111111 *
1%
#8280
b0 &
b0 *
0%
#8300
b1111111111111111 &
b1111111111111111 *
1%
0!
0$
#8320
b0 &
b0 *
0%
#8340
b1111111111111111 &
b1111111111111111 *
1%
#8350
b1111111111111111 "
b1111111111111111 +
b1111111111111111 ,
1#
1-
1!
1$
#8360
b0 &
b0 *
0%
#8380
b1111111111111111 &
b1111111111111111 *
1%
#8400
b0 &
b0 *
0%
0!
0$
#8420
b1111111111111111 &
b1111111111111111 *
1%
#8440
b0 &
b0 *
0%
#8450
0#
0-
b0 "
b0 +
b0 ,
1!
1$
#8460
b1111111111111111 &
b1111111111111111 *
1%
#8480
b0 &
b0 *
0%
#8500
b1111111111111111 &
b1111111111111111 *
1%
0!
0$
#8520
b0 &
b0 *
0%
#8540
b1111111111111111 &
b1111111111111111 *
1%
#8550
b1111111111111111 "
b1111111111111111 +
b1111111111111111 ,
1#
1-
1!
1$
#8560
b0 &
b0 *
0%
#8580
b1111111111111111 &
b1111111111111111 *
1%
#8600
b0 &
b0 *
0%
0!
0$
#8620
b1111111111111111 &
b1111111111111111 *
1%
#8640
b0 &
b0 *
0%
#8650
0#
0-
b0 "
b0 +
b0 ,
1!
1$
#8660
b1111111111111111 &
b1111111111111111 *
1%
#8680
b0 &
b0 *
0%
#8700
b1111111111111111 &
b1111111111111111 *
1%
0!
0$
#8720
b0 &
b0 *
0%
#8740
b1111111111111111 &
b1111111111111111 *
1%
#8750
b1111111111111111 "
b1111111111111111 +
b1111111111111111 ,
1#
1-
1!
1$
#8760
b0 &
b0 *
0%
